image-functions/Functions.py
image-functions/__init__.py
image_functions/Functions.py
image_functions/__init__.py
image_functions_barel-0.0.4.dist-info/LICENSE
image_functions_barel-0.0.4.dist-info/METADATA
image_functions_barel-0.0.4.dist-info/WHEEL
image_functions_barel-0.0.4.dist-info/top_level.txt
image_functions_barel-0.0.4.dist-info/RECORD
